munkres_rmsd/RMSD.py
munkres_rmsd/__init__.py
munkres_rmsd-0.0.1.post4.dev0.dist-info/LICENSE.md
munkres_rmsd-0.0.1.post4.dev0.dist-info/METADATA
munkres_rmsd-0.0.1.post4.dev0.dist-info/WHEEL
munkres_rmsd-0.0.1.post4.dev0.dist-info/top_level.txt
munkres_rmsd-0.0.1.post4.dev0.dist-info/RECORD
