Metadata-Version: 2.1
Name: munkres-rmsd
Version: 0.0.1.post4.dev0
Summary: Proper RMSD calculation between molecules using the Kuhn-Munkres Hungarian algorithm.
Home-page: https://github.com/OlivierBeq/RMSD
Author: Olivier J.M. Béquignon
Author-email: olivier.bequignon.maintainer@gmail.com
Maintainer: Olivier J.M. Béquignon
Maintainer-email: olivier.bequignon.maintainer@gmail.com
License: MIT
Keywords: RMSD,docking poses,atom mapping
Classifier: Development Status :: 2 - Pre-Alpha
Classifier: Programming Language :: Python
Classifier: Programming Language :: Python :: 3.9
Classifier: Programming Language :: Python :: 3.8
Classifier: Programming Language :: Python :: 3.7
Classifier: Programming Language :: Python :: 3.6
License-File: LICENSE.md
Requires-Dist: numpy
Requires-Dist: scipy
Requires-Dist: rdkit
Provides-Extra: docs
Requires-Dist: sphinx ; extra == 'docs'
Requires-Dist: sphinx-rtd-theme ; extra == 'docs'
Requires-Dist: sphinx-autodoc-typehints ; extra == 'docs'
Provides-Extra: testing
Requires-Dist: pytest ; extra == 'testing'
